{
  "main": {
    "id": "6b0399bd3fc2ba21",
    "type": "split",
    "children": [
      {
        "id": "944efb5366eac674",
        "type": "tabs",
        "children": [
          {
            "id": "4e487f8f13e681ac",
            "type": "leaf",
            "state": {
              "type": "markdown",
              "state": {
                "file": "1.md",
                "mode": "source",
                "source": false
              }
            }
          }
        ]
      }
    ],
    "direction": "vertical"
  },
  "left": {
    "id": "42c7579749a581d6",
    "type": "mobile-drawer",
    "children": [
      {
        "id": "c8ab86d88301766e",
        "type": "leaf",
        "state": {
          "type": "file-explorer",
          "state": {
            "sortOrder": "alphabetical"
          }
        }
      },
      {
        "id": "4fda8f72ca7d695c",
        "type": "leaf",
        "state": {
          "type": "search",
          "state": {
            "query": "",
            "matchingCase": false,
            "explainSearch": false,
            "collapseAll": false,
            "extraContext": false,
            "sortOrder": "alphabetical"
          }
        }
      },
      {
        "id": "da2586de8207f991",
        "type": "leaf",
        "state": {
          "type": "tag",
          "state": {
            "sortOrder": "frequency",
            "useHierarchy": true
          }
        }
      },
      {
        "id": "60dc94acdf338dac",
        "type": "leaf",
        "state": {
          "type": "bookmarks",
          "state": {}
        }
      }
    ],
    "currentTab": 0
  },
  "right": {
    "id": "b82e085288f21ec4",
    "type": "mobile-drawer",
    "children": [
      {
        "id": "4ef539ad130e8221",
        "type": "leaf",
        "state": {
          "type": "backlink",
          "state": {
            "file": "1.md",
            "collapseAll": false,
            "extraContext": false,
            "sortOrder": "alphabetical",
            "showSearch": false,
            "searchQuery": "",
            "backlinkCollapsed": false,
            "unlinkedCollapsed": true
          }
        }
      },
      {
        "id": "38c4edddbc4a044f",
        "type": "leaf",
        "state": {
          "type": "outgoing-link",
          "state": {
            "file": "1.md",
            "linksCollapsed": false,
            "unlinkedCollapsed": true
          }
        }
      },
      {
        "id": "28703eb2dcebf325",
        "type": "leaf",
        "state": {
          "type": "outline",
          "state": {
            "file": "1.md"
          }
        }
      }
    ],
    "currentTab": 0
  },
  "left-ribbon": {
    "hiddenItems": {
      "switcher:Open quick switcher": false,
      "graph:Open graph view": false,
      "canvas:Create new canvas": false,
      "daily-notes:Open today's daily note": false,
      "templates:Insert template": false,
      "command-palette:Open command palette": false
    }
  },
  "active": "4e487f8f13e681ac",
  "lastOpenFiles": [
    "Main.md",
    "/Main.md",
    "Thissa.md",
    "/Thissa.md"
  ]
}